immich_face_to_album/__main__.py
immich_face_to_album-1.0.13.dist-info/licenses/LICENCE.txt
immich_face_to_album-1.0.13.dist-info/METADATA
immich_face_to_album-1.0.13.dist-info/WHEEL
immich_face_to_album-1.0.13.dist-info/entry_points.txt
immich_face_to_album-1.0.13.dist-info/top_level.txt
immich_face_to_album-1.0.13.dist-info/RECORD
